{"updated":1781491143,"items":{"mex":{"159":{"interval":42240,"last":1781479804,"n":7,"rel":"low","sellReady":true,"sellRate":0.1724137931034483,"srel":"low","secToSellout":4262,"modelQty":845,"n2":29,"obsSec":1740,"maxDropShare":1,"sumDrops":5},"258":{"interval":2460,"last":1781489524,"n":23,"rel":"med","sellReady":true,"sellRate":48.035714285714285,"srel":"high","secToSellout":18,"modelQty":1006,"n2":28,"obsSec":1680,"maxDropShare":0.11291460832745237,"sumDrops":1345},"259":{"interval":4560,"last":1781487604,"n":22,"rel":"low","sellReady":true,"sellRate":0.6206896551724138,"srel":"med","secToSellout":136,"modelQty":97,"n2":29,"obsSec":1740,"maxDropShare":0.41975308641975306,"sumDrops":18},"260":{"interval":17939,"last":1781487004,"n":23,"rel":"low","sellReady":true,"sellRate":16.862068965517242,"srel":"high","secToSellout":442,"modelQty":8562,"n2":29,"obsSec":1740,"maxDropShare":0.16134751773049646,"sumDrops":489},"409":{"interval":75096,"last":1781489224,"n":5,"rel":"med","sellReady":false},"426":{"interval":25805,"last":1781478604,"n":16,"rel":"med","sellReady":true,"sellRate":0.5172413793103449,"srel":"high","secToSellout":42,"modelQty":25,"n2":29,"obsSec":1740,"maxDropShare":0.37662337662337664,"sumDrops":15},"432":{"interval":36431,"last":1781484964,"n":13,"rel":"low","sellReady":true,"sellRate":0.3448275862068966,"srel":"low","secToSellout":2272,"modelQty":901,"n2":29,"obsSec":1740,"maxDropShare":0.6052631578947368,"sumDrops":10},"1125":{"interval":26658,"last":1781478304,"n":14,"rel":"low","sellReady":true,"sellRate":3.5517241379310347,"srel":"high","secToSellout":2036,"modelQty":8318,"n2":29,"obsSec":1740,"maxDropShare":0.37142857142857144,"sumDrops":103},"1429":{"interval":19079,"last":1781474044,"n":23,"rel":"med","sellReady":false}},"cay":{"613":{"sellReady":true,"sellRate":0.1724137931034483,"srel":"low","secToSellout":348,"modelQty":69,"n2":29,"obsSec":1740,"maxDropShare":1,"sumDrops":5},"616":{"interval":2280,"last":1781489764,"n":22,"rel":"high","sellReady":true,"sellRate":3.4285714285714284,"srel":"high","secToSellout":9,"modelQty":34,"n2":28,"obsSec":1680,"maxDropShare":0.29310344827586204,"sumDrops":96},"617":{"interval":9388,"last":1781475424,"n":22,"rel":"low","sellReady":true,"sellRate":14.586206896551724,"srel":"high","secToSellout":65,"modelQty":1087,"n2":29,"obsSec":1740,"maxDropShare":0.15991471215351813,"sumDrops":423},"618":{"interval":2400,"last":1781488624,"n":22,"rel":"high","sellReady":true,"sellRate":39,"srel":"high","secToSellout":0,"modelQty":0,"n2":29,"obsSec":1740,"maxDropShare":0.1254071661237785,"sumDrops":1131},"619":{"interval":7380,"last":1781486764,"n":23,"rel":"med","sellReady":false},"620":{"interval":2280,"last":1781482624,"n":23,"rel":"med","sellReady":true,"sellRate":0.1724137931034483,"srel":"low","secToSellout":86,"modelQty":17,"n2":29,"obsSec":1740,"maxDropShare":1,"sumDrops":5},"622":{"interval":36481,"last":1781488384,"n":7,"rel":"low","sellReady":false},"623":{"interval":39746,"last":1781481664,"n":6,"rel":"low","sellReady":false},"624":{"interval":33960,"last":1781475484,"n":12,"rel":"low","sellReady":false},"626":{"interval":41040,"last":1781475484,"n":9,"rel":"low","sellReady":false},"1482":{"interval":21060,"last":1781475424,"n":13,"rel":"low","sellReady":true,"sellRate":0.2413793103448276,"srel":"low","secToSellout":7731,"modelQty":2146,"n2":29,"obsSec":1740,"maxDropShare":0.7142857142857143,"sumDrops":7}},"uni":{"206":{"interval":8460,"last":1781481608,"n":23,"rel":"med","sellReady":false},"266":{"interval":2520,"last":1781488144,"n":23,"rel":"med","sellReady":true,"sellRate":53.93103448275862,"srel":"high","secToSellout":0,"modelQty":0,"n2":29,"obsSec":1740,"maxDropShare":0.11367673179396093,"sumDrops":1564},"267":{"sellReady":true,"sellRate":4.862068965517241,"srel":"high","secToSellout":36,"modelQty":202,"n2":29,"obsSec":1740,"maxDropShare":0.3925619834710744,"sumDrops":141},"268":{"interval":2760,"last":1781491084,"n":23,"rel":"med","sellReady":true,"sellRate":11.642857142857142,"srel":"high","secToSellout":187,"modelQty":2500,"n2":28,"obsSec":1680,"maxDropShare":0.23160762942779292,"sumDrops":326},"411":{"interval":32760,"last":1781475004,"n":9,"rel":"low","sellReady":false},"431":{"interval":26400,"last":1781472304,"n":13,"rel":"low","sellReady":false},"1501":{"interval":88860,"last":1781488684,"n":5,"rel":"low","sellReady":true,"sellRate":5.241379310344827,"srel":"high","secToSellout":129,"modelQty":779,"n2":29,"obsSec":1740,"maxDropShare":0.2085889570552147,"sumDrops":152}},"arg":{"196":{"interval":26305,"last":1781490544,"n":16,"rel":"low","sellReady":true,"sellRate":0.17857142857142858,"srel":"low","secToSellout":4826,"modelQty":991,"n2":28,"obsSec":1680,"maxDropShare":1,"sumDrops":5},"199":{"sellReady":true,"sellRate":0.3448275862068966,"srel":"med","secToSellout":343,"modelQty":136,"n2":29,"obsSec":1740,"maxDropShare":0.5740740740740741,"sumDrops":10},"256":{"interval":1260,"last":1781490724,"n":23,"rel":"high","sellReady":true,"sellRate":4.296296296296297,"srel":"high","secToSellout":4,"modelQty":20,"n2":27,"obsSec":1620,"maxDropShare":0.32222222222222224,"sumDrops":116},"269":{"interval":2760,"last":1781488684,"n":22,"rel":"high","sellReady":true,"sellRate":50.37931034482759,"srel":"high","secToSellout":0,"modelQty":0,"n2":29,"obsSec":1740,"maxDropShare":0.20342857142857143,"sumDrops":1461},"407":{"interval":17700,"last":1781486764,"n":23,"rel":"med","sellReady":false},"1487":{"interval":53551,"last":1781479684,"n":8,"rel":"med","sellReady":false},"1488":{"sellReady":true,"sellRate":0.1724137931034483,"srel":"low","secToSellout":2718,"modelQty":539,"n2":29,"obsSec":1740,"maxDropShare":1,"sumDrops":5},"1503":{"sellReady":true,"sellRate":0.3448275862068966,"srel":"med","secToSellout":946,"modelQty":375,"n2":29,"obsSec":1740,"maxDropShare":0.5961538461538461,"sumDrops":10}},"swi":{"196":{"sellReady":true,"sellRate":0.3448275862068966,"srel":"low","secToSellout":948,"modelQty":376,"n2":29,"obsSec":1740,"maxDropShare":0.7142857142857143,"sumDrops":10},"222":{"interval":2580,"last":1781490664,"n":23,"rel":"med","sellReady":true,"sellRate":6.428571428571429,"srel":"high","secToSellout":54,"modelQty":396,"n2":28,"obsSec":1680,"maxDropShare":0.23107569721115537,"sumDrops":180},"272":{"interval":17220,"last":1781480104,"n":23,"rel":"med","sellReady":true,"sellRate":13.96551724137931,"srel":"high","secToSellout":385,"modelQty":6190,"n2":29,"obsSec":1740,"maxDropShare":0.18345323741007194,"sumDrops":405},"273":{"interval":2161,"last":1781489644,"n":23,"rel":"high","sellReady":true,"sellRate":46.57142857142857,"srel":"high","secToSellout":19,"modelQty":999,"n2":28,"obsSec":1680,"maxDropShare":0.12691771269177127,"sumDrops":1304},"361":{"interval":7860,"last":1781490064,"n":23,"rel":"med","sellReady":true,"sellRate":0.10714285714285714,"srel":"low","secToSellout":0,"modelQty":0,"n2":28,"obsSec":1680,"maxDropShare":1,"sumDrops":3},"1489":{"interval":7440,"last":1781489464,"n":22,"rel":"med","sellReady":true,"sellRate":14.357142857142858,"srel":"high","secToSellout":30,"modelQty":496,"n2":28,"obsSec":1680,"maxDropShare":0.16421052631578947,"sumDrops":402},"1491":{"interval":15900,"last":1781472844,"n":23,"rel":"med","sellReady":false}},"jap":{"197":{"interval":48780,"last":1781485744,"n":9,"rel":"med","sellReady":false},"204":{"sellReady":true,"sellRate":0.10344827586206896,"srel":"low","secToSellout":7027,"modelQty":836,"n2":29,"obsSec":1740,"maxDropShare":1,"sumDrops":3},"206":{"interval":8700,"last":1781488924,"n":23,"rel":"high","sellReady":true,"sellRate":31,"srel":"high","secToSellout":0,"modelQty":0,"n2":29,"obsSec":1740,"maxDropShare":0.13539445628997868,"sumDrops":899},"235":{"interval":96480,"last":1781470624,"n":3,"rel":"low","sellReady":false},"277":{"interval":16140,"last":1781480764,"n":22,"rel":"med","sellReady":true,"sellRate":14.689655172413794,"srel":"high","secToSellout":323,"modelQty":5459,"n2":29,"obsSec":1740,"maxDropShare":0.13513513513513514,"sumDrops":426},"294":{"interval":17700,"last":1781482504,"n":23,"rel":"med","sellReady":false},"427":{"interval":7346,"last":1781490904,"n":22,"rel":"med","sellReady":true,"sellRate":0.17857142857142858,"srel":"low","secToSellout":302,"modelQty":62,"n2":28,"obsSec":1680,"maxDropShare":1,"sumDrops":5},"429":{"interval":16500,"last":1781488384,"n":23,"rel":"med","sellReady":false},"437":{"interval":21240,"last":1781480104,"n":19,"rel":"med","sellReady":true,"sellRate":0.1724137931034483,"srel":"low","secToSellout":4231,"modelQty":839,"n2":29,"obsSec":1740,"maxDropShare":1,"sumDrops":5},"1249":{"sellReady":true,"sellRate":4.413793103448276,"srel":"high","secToSellout":1731,"modelQty":8784,"n2":29,"obsSec":1740,"maxDropShare":0.27906976744186046,"sumDrops":128},"1492":{"interval":13020,"last":1781483344,"n":23,"rel":"high","sellReady":true,"sellRate":7.655172413793103,"srel":"high","secToSellout":78,"modelQty":689,"n2":29,"obsSec":1740,"maxDropShare":0.22727272727272727,"sumDrops":222},"1493":{"interval":17221,"last":1781489944,"n":23,"rel":"med","sellReady":true,"sellRate":0.35714285714285715,"srel":"low","secToSellout":5999,"modelQty":2464,"n2":28,"obsSec":1680,"maxDropShare":0.8055555555555556,"sumDrops":10}},"chi":{"197":{"sellReady":true,"sellRate":0.1724137931034483,"srel":"low","secToSellout":3001,"modelQty":595,"n2":29,"obsSec":1740,"maxDropShare":1,"sumDrops":5},"246":{"interval":47678,"last":1781476624,"n":9,"rel":"low","sellReady":false},"274":{"interval":2820,"last":1781489764,"n":23,"rel":"high","sellReady":true,"sellRate":37.392857142857146,"srel":"high","secToSellout":27,"modelQty":1156,"n2":28,"obsSec":1680,"maxDropShare":0.1633187772925764,"sumDrops":1047},"275":{"interval":32448,"last":1781470144,"n":12,"rel":"med","sellReady":false},"276":{"sellReady":true,"sellRate":16.551724137931036,"srel":"high","secToSellout":89,"modelQty":1689,"n2":29,"obsSec":1740,"maxDropShare":0.2534775888717156,"sumDrops":480},"1462":{"sellReady":true,"sellRate":0.3448275862068966,"srel":"low","secToSellout":4822,"modelQty":1912,"n2":29,"obsSec":1740,"maxDropShare":0.6041666666666666,"sumDrops":10},"1494":{"interval":8700,"last":1781486164,"n":23,"rel":"high","sellReady":true,"sellRate":11.724137931034482,"srel":"high","secToSellout":68,"modelQty":920,"n2":29,"obsSec":1740,"maxDropShare":0.14030612244897958,"sumDrops":340},"1498":{"sellReady":true,"sellRate":0.3448275862068966,"srel":"low","secToSellout":880,"modelQty":349,"n2":29,"obsSec":1740,"maxDropShare":0.6153846153846154,"sumDrops":10}},"uae":{"384":{"interval":2700,"last":1781489764,"n":23,"rel":"high","sellReady":true,"sellRate":43,"srel":"high","secToSellout":19,"modelQty":925,"n2":28,"obsSec":1680,"maxDropShare":0.15363511659807957,"sumDrops":1204},"412":{"interval":55140,"last":1781484544,"n":6,"rel":"low","sellReady":false},"1264":{"sellReady":true,"sellRate":0.4482758620689655,"srel":"med","secToSellout":1620,"modelQty":835,"n2":29,"obsSec":1740,"maxDropShare":0.5340909090909091,"sumDrops":13},"1496":{"sellReady":true,"sellRate":3.4827586206896552,"srel":"high","secToSellout":280,"modelQty":1122,"n2":29,"obsSec":1740,"maxDropShare":0.35766423357664234,"sumDrops":101}},"sou":{"226":{"interval":19140,"last":1781479984,"n":23,"rel":"med","sellReady":true,"sellRate":6.931034482758621,"srel":"high","secToSellout":128,"modelQty":1019,"n2":29,"obsSec":1740,"maxDropShare":0.22140221402214022,"sumDrops":201},"280":{"interval":6000,"last":1781489164,"n":23,"rel":"low","sellReady":false},"281":{"interval":2880,"last":1781487784,"n":23,"rel":"high","sellReady":true,"sellRate":16.448275862068964,"srel":"high","secToSellout":0,"modelQty":0,"n2":29,"obsSec":1740,"maxDropShare":0.2483766233766234,"sumDrops":477},"282":{"interval":18960,"last":1781482444,"n":23,"rel":"med","sellReady":true,"sellRate":30.896551724137932,"srel":"high","secToSellout":166,"modelQty":5893,"n2":29,"obsSec":1740,"maxDropShare":0.13903192584963955,"sumDrops":896},"332":{"interval":66111,"last":1781478244,"n":7,"rel":"med","sellReady":true,"sellRate":0.3793103448275862,"srel":"med","secToSellout":23,"modelQty":10,"n2":29,"obsSec":1740,"maxDropShare":0.5333333333333333,"sumDrops":11},"358":{"interval":17040,"last":1781471884,"n":23,"rel":"high","sellReady":false},"652":{"interval":31980,"last":1781473444,"n":11,"rel":"med","sellReady":false},"1497":{"interval":39810,"last":1781475364,"n":10,"rel":"low","sellReady":true,"sellRate":0.5172413793103449,"srel":"med","secToSellout":3403,"modelQty":2024,"n2":29,"obsSec":1740,"maxDropShare":0.5,"sumDrops":15}},"can":{"196":{"interval":12600,"last":1781480104,"n":23,"rel":"low","sellReady":false},"206":{"interval":12420,"last":1781487484,"n":19,"rel":"low","sellReady":true,"sellRate":0.13793103448275862,"srel":"low","secToSellout":15616,"modelQty":2477,"n2":29,"obsSec":1740,"maxDropShare":1,"sumDrops":4},"261":{"interval":2460,"last":1781490964,"n":23,"rel":"high","sellReady":true,"sellRate":16.821428571428573,"srel":"high","secToSellout":122,"modelQty":2366,"n2":28,"obsSec":1680,"maxDropShare":0.2375886524822695,"sumDrops":471},"262":{"interval":14100,"last":1781471404,"n":23,"rel":"low","sellReady":true,"sellRate":0.3448275862068966,"srel":"low","secToSellout":0,"modelQty":0,"n2":29,"obsSec":1740,"maxDropShare":0.6521739130434783,"sumDrops":10},"263":{"interval":8520,"last":1781472784,"n":23,"rel":"low","sellReady":true,"sellRate":11.655172413793103,"srel":"high","secToSellout":162,"modelQty":2169,"n2":29,"obsSec":1740,"maxDropShare":0.3181818181818182,"sumDrops":338},"328":{"interval":18180,"last":1781484544,"n":17,"rel":"low","sellReady":true,"sellRate":0.3103448275862069,"srel":"med","secToSellout":1309,"modelQty":467,"n2":29,"obsSec":1740,"maxDropShare":0.5555555555555556,"sumDrops":9},"410":{"interval":29280,"last":1781486104,"n":9,"rel":"low","sellReady":true,"sellRate":0.1724137931034483,"srel":"low","secToSellout":192,"modelQty":38,"n2":29,"obsSec":1740,"maxDropShare":1,"sumDrops":5},"1348":{"interval":13950,"last":1781475484,"n":22,"rel":"low","sellReady":true,"sellRate":0.5172413793103449,"srel":"high","secToSellout":2873,"modelQty":1709,"n2":29,"obsSec":1740,"maxDropShare":0.37681159420289856,"sumDrops":15},"1483":{"interval":10920,"last":1781487124,"n":23,"rel":"med","sellReady":true,"sellRate":24.655172413793103,"srel":"high","secToSellout":22,"modelQty":629,"n2":29,"obsSec":1740,"maxDropShare":0.13274336283185842,"sumDrops":715},"1484":{"interval":10800,"last":1781479624,"n":23,"rel":"med","sellReady":true,"sellRate":0.1724137931034483,"srel":"low","secToSellout":0,"modelQty":0,"n2":29,"obsSec":1740,"maxDropShare":1,"sumDrops":5}},"haw":{"241":{"interval":28680,"last":1781480044,"n":9,"rel":"low","sellReady":false},"264":{"interval":13911,"last":1781473624,"n":23,"rel":"low","sellReady":true,"sellRate":26.310344827586206,"srel":"high","secToSellout":67,"modelQty":2023,"n2":29,"obsSec":1740,"maxDropShare":0.13761467889908258,"sumDrops":763},"265":{"interval":17220,"last":1781478304,"n":23,"rel":"low","sellReady":true,"sellRate":0.4482758620689655,"srel":"med","secToSellout":217,"modelQty":112,"n2":29,"obsSec":1740,"maxDropShare":0.5686274509803921,"sumDrops":13},"421":{"interval":27120,"last":1781473804,"n":15,"rel":"low","sellReady":false},"1485":{"interval":8400,"last":1781485564,"n":23,"rel":"high","sellReady":false},"1486":{"interval":8401,"last":1781488204,"n":23,"rel":"med","sellReady":true,"sellRate":0.5172413793103449,"srel":"low","secToSellout":0,"modelQty":0,"n2":29,"obsSec":1740,"maxDropShare":0.7910447761194029,"sumDrops":15},"1502":{"sellReady":true,"sellRate":1.103448275862069,"srel":"high","secToSellout":272,"modelQty":345,"n2":29,"obsSec":1740,"maxDropShare":0.34523809523809523,"sumDrops":32}}}}