{"updated":1784339703,"items":{"mex":{"8":{"interval":6211,"last":1784333965,"n":22,"rel":"low","sellReady":false},"11":{"interval":4321,"last":1784337844,"n":23,"rel":"low","sellReady":false},"20":{"interval":64020,"last":1784338624,"n":23,"rel":"low","sellReady":true,"sellRate":0.21428571428571427,"srel":"med","secToSellout":24,"modelQty":6,"n2":28,"obsSec":1680,"maxDropShare":0.5,"sumDrops":6},"26":{"interval":7740,"last":1784338624,"n":23,"rel":"low","sellReady":true,"sellRate":0.39285714285714285,"srel":"med","secToSellout":60,"modelQty":27,"n2":28,"obsSec":1680,"maxDropShare":0.4864864864864865,"sumDrops":11},"50":{"interval":36481,"last":1784319505,"n":23,"rel":"low","sellReady":false},"99":{"interval":54649,"last":1784339104,"n":21,"rel":"low","sellReady":false},"111":{"interval":5880,"last":1784333725,"n":23,"rel":"low","sellReady":false},"159":{"interval":22440,"last":1784338624,"n":21,"rel":"low","sellReady":true,"sellRate":0.35714285714285715,"srel":"med","secToSellout":1902,"modelQty":781,"n2":28,"obsSec":1680,"maxDropShare":0.5,"sumDrops":10},"178":{"interval":7500,"last":1784335525,"n":23,"rel":"low","sellReady":false},"258":{"interval":3060,"last":1784338804,"n":23,"rel":"high","sellReady":true,"sellRate":23,"srel":"high","secToSellout":61,"modelQty":1619,"n2":28,"obsSec":1680,"maxDropShare":0.1963677639046538,"sumDrops":644},"259":{"interval":4740,"last":1784338624,"n":23,"rel":"med","sellReady":true,"sellRate":4.857142857142857,"srel":"med","secToSellout":5,"modelQty":27,"n2":28,"obsSec":1680,"maxDropShare":0.46062992125984253,"sumDrops":136},"260":{"interval":11761,"last":1784338624,"n":21,"rel":"low","sellReady":true,"sellRate":28,"srel":"med","secToSellout":121,"modelQty":3902,"n2":28,"obsSec":1680,"maxDropShare":0.4528985507246377,"sumDrops":784},"426":{"interval":21241,"last":1784339104,"n":23,"rel":"low","sellReady":false},"432":{"interval":24386,"last":1784338624,"n":20,"rel":"low","sellReady":true,"sellRate":1.4285714285714286,"srel":"high","secToSellout":204,"modelQty":335,"n2":28,"obsSec":1680,"maxDropShare":0.3023255813953488,"sumDrops":40},"640":{"interval":52621,"last":1784319505,"n":23,"rel":"low","sellReady":false},"1125":{"interval":21060,"last":1784338624,"n":22,"rel":"low","sellReady":true,"sellRate":5,"srel":"med","secToSellout":0,"modelQty":0,"n2":28,"obsSec":1680,"maxDropShare":0.526813880126183,"sumDrops":140},"1429":{"interval":14161,"last":1784324905,"n":22,"rel":"med","sellReady":false},"1499":{"interval":29075,"last":1784338624,"n":23,"rel":"low","sellReady":true,"sellRate":0.5714285714285714,"srel":"high","secToSellout":320,"modelQty":210,"n2":28,"obsSec":1680,"maxDropShare":0.3333333333333333,"sumDrops":16}},"cay":{"612":{"interval":15659,"last":1784330185,"n":23,"rel":"low","sellReady":false},"614":{"interval":6510,"last":1784332825,"n":22,"rel":"low","sellReady":false},"616":{"interval":2820,"last":1784336125,"n":23,"rel":"high","sellReady":true,"sellRate":0.3448275862068966,"srel":"med","secToSellout":0,"modelQty":0,"n2":29,"obsSec":1740,"maxDropShare":0.5909090909090909,"sumDrops":10},"617":{"interval":16920,"last":1784336965,"n":23,"rel":"low","sellReady":true,"sellRate":19.586206896551722,"srel":"high","secToSellout":182,"modelQty":4103,"n2":29,"obsSec":1740,"maxDropShare":0.22083333333333333,"sumDrops":568},"618":{"interval":2580,"last":1784338564,"n":23,"rel":"high","sellReady":true,"sellRate":37,"srel":"high","secToSellout":32,"modelQty":1381,"n2":28,"obsSec":1680,"maxDropShare":0.12421805183199285,"sumDrops":1036},"619":{"interval":7501,"last":1784322565,"n":22,"rel":"low","sellReady":true,"sellRate":0.1724137931034483,"srel":"low","secToSellout":0,"modelQty":0,"n2":29,"obsSec":1740,"maxDropShare":1,"sumDrops":5},"620":{"interval":2820,"last":1784339104,"n":23,"rel":"med","sellReady":true,"sellRate":1.7142857142857142,"srel":"high","secToSellout":49,"modelQty":96,"n2":28,"obsSec":1680,"maxDropShare":0.33707865168539325,"sumDrops":48},"624":{"interval":53341,"last":1784339044,"n":23,"rel":"low","sellReady":false},"625":{"interval":175987,"last":1784332886,"n":23,"rel":"low","sellReady":false},"1482":{"sellReady":true,"sellRate":0.20689655172413793,"srel":"low","secToSellout":17640,"modelQty":4197,"n2":29,"obsSec":1740,"maxDropShare":0.6666666666666666,"sumDrops":6}},"uni":{"217":{"interval":2879,"last":1784339044,"n":23,"rel":"low","sellReady":false},"219":{"interval":19741,"last":1784331445,"n":23,"rel":"low","sellReady":false},"220":{"interval":12180,"last":1784339044,"n":22,"rel":"low","sellReady":true,"sellRate":0.32142857142857145,"srel":"low","secToSellout":1645,"modelQty":608,"n2":28,"obsSec":1680,"maxDropShare":0.8260869565217391,"sumDrops":9},"221":{"interval":8100,"last":1784327245,"n":21,"rel":"low","sellReady":false},"266":{"interval":3240,"last":1784338084,"n":23,"rel":"med","sellReady":true,"sellRate":27.678571428571427,"srel":"high","secToSellout":46,"modelQty":1453,"n2":28,"obsSec":1680,"maxDropShare":0.18379446640316205,"sumDrops":775},"267":{"sellReady":true,"sellRate":8.862068965517242,"srel":"high","secToSellout":16,"modelQty":168,"n2":29,"obsSec":1740,"maxDropShare":0.15942028985507245,"sumDrops":257},"268":{"interval":3120,"last":1784337844,"n":23,"rel":"med","sellReady":true,"sellRate":27.620689655172413,"srel":"high","secToSellout":50,"modelQty":1578,"n2":29,"obsSec":1740,"maxDropShare":0.18921892189218922,"sumDrops":801},"408":{"interval":46620,"last":1784336725,"n":23,"rel":"med","sellReady":false},"411":{"interval":24300,"last":1784330425,"n":21,"rel":"low","sellReady":false},"415":{"interval":45660,"last":1784322385,"n":23,"rel":"med","sellReady":false},"416":{"interval":41460,"last":1784330785,"n":21,"rel":"low","sellReady":false},"431":{"interval":21931,"last":1784332585,"n":23,"rel":"low","sellReady":false}},"arg":{"196":{"interval":16020,"last":1784334925,"n":22,"rel":"low","sellReady":false},"198":{"interval":42711,"last":1784331565,"n":21,"rel":"low","sellReady":false},"199":{"interval":36360,"last":1784331565,"n":21,"rel":"low","sellReady":false},"203":{"interval":109639,"last":1784331565,"n":21,"rel":"low","sellReady":false},"256":{"interval":1200,"last":1784337964,"n":22,"rel":"high","sellReady":true,"sellRate":2.8214285714285716,"srel":"high","secToSellout":0,"modelQty":0,"n2":28,"obsSec":1680,"maxDropShare":0.27,"sumDrops":79},"269":{"interval":2160,"last":1784336725,"n":23,"rel":"med","sellReady":true,"sellRate":34.06896551724138,"srel":"high","secToSellout":1,"modelQty":20,"n2":29,"obsSec":1740,"maxDropShare":0.12409420289855072,"sumDrops":988},"271":{"interval":5640,"last":1784334925,"n":23,"rel":"low","sellReady":true,"sellRate":0.8620689655172413,"srel":"med","secToSellout":2109,"modelQty":2091,"n2":29,"obsSec":1740,"maxDropShare":0.49523809523809526,"sumDrops":25},"391":{"interval":1020,"last":1784331565,"n":21,"rel":"low","sellReady":false},"407":{"interval":8580,"last":1784319505,"n":21,"rel":"low","sellReady":false},"1466":{"interval":13560,"last":1784334925,"n":21,"rel":"low","sellReady":true,"sellRate":0.1724137931034483,"srel":"low","secToSellout":2678,"modelQty":531,"n2":29,"obsSec":1740,"maxDropShare":1,"sumDrops":5},"1487":{"interval":11011,"last":1784331565,"n":20,"rel":"low","sellReady":false},"1488":{"interval":35490,"last":1784334985,"n":22,"rel":"low","sellReady":false}},"swi":{"196":{"interval":21239,"last":1784331565,"n":21,"rel":"low","sellReady":false},"222":{"interval":2820,"last":1784338924,"n":23,"rel":"high","sellReady":true,"sellRate":2.5714285714285716,"srel":"high","secToSellout":132,"modelQty":391,"n2":28,"obsSec":1680,"maxDropShare":0.3,"sumDrops":72},"224":{"interval":2040,"last":1784339644,"n":21,"rel":"low","sellReady":false},"272":{"interval":8041,"last":1784327485,"n":20,"rel":"low","sellReady":true,"sellRate":24.551724137931036,"srel":"high","secToSellout":179,"modelQty":5060,"n2":29,"obsSec":1740,"maxDropShare":0.23582474226804123,"sumDrops":712},"273":{"interval":2280,"last":1784338384,"n":23,"rel":"high","sellReady":true,"sellRate":48.5,"srel":"high","secToSellout":19,"modelQty":1032,"n2":28,"obsSec":1680,"maxDropShare":0.1119718309859155,"sumDrops":1358},"1489":{"interval":6181,"last":1784335765,"n":18,"rel":"low","sellReady":true,"sellRate":8.793103448275861,"srel":"high","secToSellout":166,"modelQty":1677,"n2":29,"obsSec":1740,"maxDropShare":0.2549019607843137,"sumDrops":255},"1490":{"interval":16080,"last":1784335465,"n":19,"rel":"low","sellReady":true,"sellRate":3.103448275862069,"srel":"high","secToSellout":47,"modelQty":169,"n2":29,"obsSec":1740,"maxDropShare":0.2631578947368421,"sumDrops":90}},"jap":{"197":{"interval":15540,"last":1784338324,"n":22,"rel":"low","sellReady":false},"200":{"interval":17250,"last":1784322445,"n":22,"rel":"low","sellReady":false},"203":{"interval":168928,"last":1784320105,"n":11,"rel":"low","sellReady":false},"205":{"interval":18751,"last":1784320105,"n":20,"rel":"low","sellReady":false},"206":{"interval":9839,"last":1784332285,"n":23,"rel":"high","sellReady":true,"sellRate":9.96551724137931,"srel":"high","secToSellout":9,"modelQty":108,"n2":29,"obsSec":1740,"maxDropShare":0.2235294117647059,"sumDrops":289},"234":{"interval":3360,"last":1784320105,"n":21,"rel":"low","sellReady":false},"235":{"interval":2850,"last":1784322925,"n":22,"rel":"low","sellReady":false},"236":{"interval":13920,"last":1784323165,"n":23,"rel":"low","sellReady":false},"238":{"interval":5070,"last":1784337904,"n":22,"rel":"low","sellReady":false},"239":{"interval":6690,"last":1784323585,"n":22,"rel":"low","sellReady":true,"sellRate":0.1724137931034483,"srel":"low","secToSellout":1210,"modelQty":240,"n2":29,"obsSec":1740,"maxDropShare":1,"sumDrops":5},"277":{"interval":7290,"last":1784335645,"n":22,"rel":"low","sellReady":true,"sellRate":19.03448275862069,"srel":"high","secToSellout":134,"modelQty":2925,"n2":29,"obsSec":1740,"maxDropShare":0.18621700879765396,"sumDrops":552},"278":{"interval":9331,"last":1784322865,"n":22,"rel":"low","sellReady":false},"279":{"interval":75060,"last":1784320105,"n":23,"rel":"low","sellReady":false},"294":{"interval":16530,"last":1784323045,"n":22,"rel":"low","sellReady":false},"395":{"interval":3690,"last":1784333485,"n":22,"rel":"low","sellReady":false},"427":{"interval":5520,"last":1784339404,"n":21,"rel":"low","sellReady":false},"429":{"interval":13231,"last":1784330725,"n":22,"rel":"med","sellReady":false},"437":{"interval":9960,"last":1784330845,"n":22,"rel":"low","sellReady":true,"sellRate":0.6551724137931034,"srel":"high","secToSellout":1047,"modelQty":789,"n2":29,"obsSec":1740,"maxDropShare":0.390625,"sumDrops":19},"1333":{"interval":23251,"last":1784320105,"n":20,"rel":"med","sellReady":true,"sellRate":0.1724137931034483,"srel":"low","secToSellout":7131,"modelQty":1414,"n2":29,"obsSec":1740,"maxDropShare":1,"sumDrops":5},"1492":{"interval":6570,"last":1784329405,"n":22,"rel":"low","sellReady":true,"sellRate":12.448275862068966,"srel":"high","secToSellout":148,"modelQty":2112,"n2":29,"obsSec":1740,"maxDropShare":0.12990196078431374,"sumDrops":361},"1493":{"interval":4734,"last":1784320105,"n":23,"rel":"low","sellReady":true,"sellRate":0.3448275862068966,"srel":"med","secToSellout":3624,"modelQty":1437,"n2":29,"obsSec":1740,"maxDropShare":0.5714285714285714,"sumDrops":10}},"chi":{"197":{"interval":22080,"last":1784326345,"n":22,"rel":"low","sellReady":false},"199":{"interval":33346,"last":1784325985,"n":21,"rel":"low","sellReady":false},"200":{"interval":7170,"last":1784325205,"n":18,"rel":"low","sellReady":false},"244":{"interval":7380,"last":1784325865,"n":21,"rel":"low","sellReady":false},"245":{"interval":1740,"last":1784336125,"n":21,"rel":"low","sellReady":false},"246":{"interval":7618,"last":1784336005,"n":20,"rel":"low","sellReady":false},"247":{"interval":870,"last":1784337904,"n":20,"rel":"low","sellReady":false},"248":{"interval":9540,"last":1784319685,"n":21,"rel":"low","sellReady":false},"249":{"interval":5401,"last":1784323345,"n":22,"rel":"low","sellReady":false},"250":{"interval":1260,"last":1784333965,"n":20,"rel":"low","sellReady":false},"251":{"interval":8719,"last":1784327485,"n":22,"rel":"low","sellReady":false},"274":{"interval":2400,"last":1784339164,"n":23,"rel":"high","sellReady":true,"sellRate":33.785714285714285,"srel":"high","secToSellout":46,"modelQty":1794,"n2":28,"obsSec":1680,"maxDropShare":0.13913913913913914,"sumDrops":946},"275":{"interval":20580,"last":1784339344,"n":21,"rel":"low","sellReady":false},"276":{"interval":6856,"last":1784329165,"n":23,"rel":"low","sellReady":true,"sellRate":17.24137931034483,"srel":"high","secToSellout":345,"modelQty":6839,"n2":29,"obsSec":1740,"maxDropShare":0.1854419410745234,"sumDrops":500},"1462":{"interval":18691,"last":1784329285,"n":18,"rel":"low","sellReady":false},"1494":{"interval":5880,"last":1784333065,"n":23,"rel":"med","sellReady":true,"sellRate":26,"srel":"high","secToSellout":0,"modelQty":0,"n2":29,"obsSec":1740,"maxDropShare":0.1997677119628339,"sumDrops":754},"1498":{"interval":8550,"last":1784329285,"n":18,"rel":"low","sellReady":true,"sellRate":0.4827586206896552,"srel":"low","secToSellout":4265,"modelQty":2368,"n2":29,"obsSec":1740,"maxDropShare":0.6444444444444445,"sumDrops":14}},"uae":{"384":{"interval":2940,"last":1784339344,"n":23,"rel":"high","sellReady":true,"sellRate":26.821428571428573,"srel":"high","secToSellout":66,"modelQty":2023,"n2":28,"obsSec":1680,"maxDropShare":0.18900343642611683,"sumDrops":751},"385":{"sellReady":true,"sellRate":3.0344827586206895,"srel":"high","secToSellout":0,"modelQty":0,"n2":29,"obsSec":1740,"maxDropShare":0.35365853658536583,"sumDrops":88},"1264":{"sellReady":true,"sellRate":0.5172413793103449,"srel":"med","secToSellout":2824,"modelQty":1680,"n2":29,"obsSec":1740,"maxDropShare":0.5304347826086957,"sumDrops":15},"1495":{"interval":23400,"last":1784324605,"n":23,"rel":"low","sellReady":true,"sellRate":4,"srel":"high","secToSellout":224,"modelQty":1031,"n2":29,"obsSec":1740,"maxDropShare":0.3509933774834437,"sumDrops":116},"1496":{"interval":22411,"last":1784331265,"n":22,"rel":"low","sellReady":true,"sellRate":5.620689655172414,"srel":"high","secToSellout":616,"modelQty":3981,"n2":29,"obsSec":1740,"maxDropShare":0.2814070351758794,"sumDrops":163}},"sou":{"4":{"interval":1980,"last":1784328205,"n":21,"rel":"low","sellReady":false},"206":{"interval":23460,"last":1784335585,"n":17,"rel":"low","sellReady":true,"sellRate":0.3103448275862069,"srel":"low","secToSellout":62,"modelQty":22,"n2":29,"obsSec":1740,"maxDropShare":0.6,"sumDrops":9},"225":{"interval":13201,"last":1784339524,"n":22,"rel":"low","sellReady":false},"226":{"interval":13740,"last":1784337604,"n":23,"rel":"low","sellReady":true,"sellRate":6.758620689655173,"srel":"med","secToSellout":280,"modelQty":2180,"n2":29,"obsSec":1740,"maxDropShare":0.4370860927152318,"sumDrops":196},"227":{"interval":2060,"last":1784338264,"n":20,"rel":"low","sellReady":false},"228":{"interval":12480,"last":1784319145,"n":23,"rel":"low","sellReady":false},"280":{"interval":3660,"last":1784331385,"n":20,"rel":"low","sellReady":false},"281":{"interval":2490,"last":1784339584,"n":22,"rel":"high","sellReady":true,"sellRate":35.214285714285715,"srel":"high","secToSellout":0,"modelQty":1,"n2":28,"obsSec":1680,"maxDropShare":0.17001675041876047,"sumDrops":986},"282":{"interval":13320,"last":1784335285,"n":21,"rel":"med","sellReady":true,"sellRate":8.724137931034482,"srel":"high","secToSellout":334,"modelQty":3350,"n2":29,"obsSec":1740,"maxDropShare":0.29155313351498635,"sumDrops":253},"358":{"interval":15120,"last":1784330485,"n":23,"rel":"med","sellReady":false},"652":{"interval":30965,"last":1784335525,"n":23,"rel":"low","sellReady":false},"1497":{"sellReady":true,"sellRate":0.6551724137931034,"srel":"med","secToSellout":2734,"modelQty":2060,"n2":29,"obsSec":1740,"maxDropShare":0.5978260869565217,"sumDrops":19},"1500":{"interval":62719,"last":1784335225,"n":22,"rel":"low","sellReady":true,"sellRate":0.5862068965517241,"srel":"high","secToSellout":1314,"modelQty":886,"n2":29,"obsSec":1740,"maxDropShare":0.375,"sumDrops":17}},"can":{"196":{"interval":9840,"last":1784337544,"n":20,"rel":"med","sellReady":true,"sellRate":0.3448275862068966,"srel":"med","secToSellout":1672,"modelQty":663,"n2":29,"obsSec":1740,"maxDropShare":0.5357142857142857,"sumDrops":10},"197":{"interval":27480,"last":1784337904,"n":18,"rel":"low","sellReady":false},"205":{"interval":35281,"last":1784337544,"n":21,"rel":"low","sellReady":false},"206":{"interval":7320,"last":1784332705,"n":23,"rel":"high","sellReady":false},"252":{"interval":11760,"last":1784337904,"n":23,"rel":"low","sellReady":false},"253":{"interval":7560,"last":1784337544,"n":19,"rel":"low","sellReady":false},"261":{"interval":2100,"last":1784339404,"n":23,"rel":"high","sellReady":true,"sellRate":14.178571428571429,"srel":"high","secToSellout":133,"modelQty":2176,"n2":28,"obsSec":1680,"maxDropShare":0.2554027504911591,"sumDrops":397},"262":{"interval":9270,"last":1784339464,"n":22,"rel":"low","sellReady":false},"263":{"interval":6900,"last":1784337604,"n":23,"rel":"low","sellReady":true,"sellRate":30.862068965517242,"srel":"high","secToSellout":227,"modelQty":8064,"n2":29,"obsSec":1740,"maxDropShare":0.13165829145728644,"sumDrops":895},"328":{"interval":31890,"last":1784337544,"n":23,"rel":"low","sellReady":true,"sellRate":0.1724137931034483,"srel":"low","secToSellout":1079,"modelQty":214,"n2":29,"obsSec":1740,"maxDropShare":1,"sumDrops":5},"410":{"interval":72985,"last":1784337604,"n":23,"rel":"med","sellReady":false},"1348":{"interval":19801,"last":1784337544,"n":21,"rel":"low","sellReady":true,"sellRate":2.3448275862068964,"srel":"high","secToSellout":172,"modelQty":464,"n2":29,"obsSec":1740,"maxDropShare":0.3125,"sumDrops":68},"1361":{"interval":26761,"last":1784337544,"n":21,"rel":"low","sellReady":true,"sellRate":0.3448275862068966,"srel":"low","secToSellout":1553,"modelQty":616,"n2":29,"obsSec":1740,"maxDropShare":0.7407407407407407,"sumDrops":10},"1483":{"interval":7200,"last":1784337844,"n":23,"rel":"med","sellReady":true,"sellRate":63.96551724137931,"srel":"high","secToSellout":41,"modelQty":3003,"n2":29,"obsSec":1740,"maxDropShare":0.08686551543694401,"sumDrops":1855},"1484":{"interval":6339,"last":1784337544,"n":23,"rel":"med","sellReady":false}},"haw":{"241":{"interval":2670,"last":1784339524,"n":22,"rel":"low","sellReady":false},"242":{"interval":2220,"last":1784335285,"n":16,"rel":"low","sellReady":true,"sellRate":0.3448275862068966,"srel":"low","secToSellout":141,"modelQty":56,"n2":29,"obsSec":1740,"maxDropShare":0.6111111111111112,"sumDrops":10},"243":{"interval":3330,"last":1784319385,"n":20,"rel":"low","sellReady":false},"264":{"interval":4019,"last":1784338984,"n":23,"rel":"low","sellReady":true,"sellRate":23.678571428571427,"srel":"high","secToSellout":338,"modelQty":9196,"n2":28,"obsSec":1680,"maxDropShare":0.16584158415841585,"sumDrops":663},"421":{"interval":17580,"last":1784331925,"n":23,"rel":"low","sellReady":true,"sellRate":0.1724137931034483,"srel":"low","secToSellout":237,"modelQty":47,"n2":29,"obsSec":1740,"maxDropShare":0.6,"sumDrops":5},"430":{"interval":24900,"last":1784325145,"n":19,"rel":"low","sellReady":false},"1485":{"interval":4980,"last":1784336725,"n":23,"rel":"high","sellReady":true,"sellRate":60.793103448275865,"srel":"high","secToSellout":0,"modelQty":0,"n2":29,"obsSec":1740,"maxDropShare":0.09159078735940011,"sumDrops":1763},"1486":{"interval":4800,"last":1784332645,"n":23,"rel":"med","sellReady":false}}}}